{
    "alpine-js-intellisense": {
        "cargoLocks": null,
        "date": null,
        "extract": null,
        "name": "alpine-js-intellisense",
        "passthru": {
            "name": "alpine-js-intellisense",
            "publisher": "adrianwilczynski"
        },
        "pinned": false,
        "src": {
            "name": "alpine-js-intellisense-1.2.0.zip",
            "sha256": "sha256-Klx5ZvV06lXIJ3Q/mzq3KBjPpdROoxDkgEu7MBO+RhI=",
            "type": "url",
            "url": "https://adrianwilczynski.gallery.vsassets.io/_apis/public/gallery/publisher/adrianwilczynski/extension/alpine-js-intellisense/1.2.0/assetbyname/Microsoft.VisualStudio.Services.VSIXPackage"
        },
        "version": "1.2.0"
    },
    "ansible": {
        "cargoLocks": null,
        "date": null,
        "extract": null,
        "name": "ansible",
        "passthru": {
            "name": "ansible",
            "publisher": "redhat"
        },
        "pinned": false,
        "src": {
            "name": "ansible-25.1.0.zip",
            "sha256": "sha256-/kLg+msRu6GvkENVu3jw9uDbfEo/x0eZgsKfXvLaO3I=",
            "type": "url",
            "url": "https://redhat.gallery.vsassets.io/_apis/public/gallery/publisher/redhat/extension/ansible/25.1.0/assetbyname/Microsoft.VisualStudio.Services.VSIXPackage"
        },
        "version": "25.1.0"
    },
    "bun-vscode": {
        "cargoLocks": null,
        "date": null,
        "extract": null,
        "name": "bun-vscode",
        "passthru": {
            "name": "bun-vscode",
            "publisher": "oven"
        },
        "pinned": false,
        "src": {
            "name": "bun-vscode-0.0.26.zip",
            "sha256": "sha256-klMkKAorWJj2o015FWbQQfpmYe4JM0UOM+WVh+YPtI4=",
            "type": "url",
            "url": "https://oven.gallery.vsassets.io/_apis/public/gallery/publisher/oven/extension/bun-vscode/0.0.26/assetbyname/Microsoft.VisualStudio.Services.VSIXPackage"
        },
        "version": "0.0.26"
    },
    "copilot": {
        "cargoLocks": null,
        "date": null,
        "extract": null,
        "name": "copilot",
        "passthru": {
            "name": "copilot",
            "publisher": "github"
        },
        "pinned": false,
        "src": {
            "name": "copilot-1.270.1376.zip",
            "sha256": "sha256-Y+l1GzVMkkfUXc5oAJx0XvqKB9SGvNavvAmPaorthtE=",
            "type": "url",
            "url": "https://github.gallery.vsassets.io/_apis/public/gallery/publisher/github/extension/copilot/1.270.1376/assetbyname/Microsoft.VisualStudio.Services.VSIXPackage"
        },
        "version": "1.270.1376"
    },
    "copilot-chat": {
        "cargoLocks": null,
        "date": null,
        "extract": null,
        "name": "copilot-chat",
        "passthru": {
            "name": "copilot-chat",
            "publisher": "github"
        },
        "pinned": false,
        "src": {
            "name": "copilot-chat-0.25.2025021301.zip",
            "sha256": "sha256-JXjd1y0OotxkcQzl70E6/hiW/0L0jXmjVwoOq9vFad4=",
            "type": "url",
            "url": "https://github.gallery.vsassets.io/_apis/public/gallery/publisher/github/extension/copilot-chat/0.25.2025021301/assetbyname/Microsoft.VisualStudio.Services.VSIXPackage"
        },
        "version": "0.25.2025021301"
    },
    "gopls": {
        "cargoLocks": null,
        "date": null,
        "extract": null,
        "name": "gopls",
        "passthru": null,
        "pinned": false,
        "src": {
            "deepClone": false,
            "fetchSubmodules": false,
            "leaveDotGit": false,
            "name": null,
            "owner": "golang",
            "repo": "tools",
            "rev": "gopls/v0.17.1",
            "sha256": "sha256-NLUIFNooOOA4LEL5nZNdP9TvDkQUqLjKi44kZtOxeuI=",
            "sparseCheckout": [],
            "type": "github"
        },
        "version": "gopls/v0.17.1"
    },
    "grafana-vscode": {
        "cargoLocks": null,
        "date": null,
        "extract": null,
        "name": "grafana-vscode",
        "passthru": {
            "name": "grafana-vscode",
            "publisher": "grafana"
        },
        "pinned": false,
        "src": {
            "name": "grafana-vscode-0.0.19.zip",
            "sha256": "sha256-TpLOMwdaEdgzWVwUcn+fO4rgLiQammWQM8LQobt8gLw=",
            "type": "url",
            "url": "https://grafana.gallery.vsassets.io/_apis/public/gallery/publisher/grafana/extension/grafana-vscode/0.0.19/assetbyname/Microsoft.VisualStudio.Services.VSIXPackage"
        },
        "version": "0.0.19"
    },
    "htmx-attributes": {
        "cargoLocks": null,
        "date": null,
        "extract": null,
        "name": "htmx-attributes",
        "passthru": {
            "name": "htmx-attributes",
            "publisher": "craigrbroughton"
        },
        "pinned": false,
        "src": {
            "name": "htmx-attributes-0.8.0.zip",
            "sha256": "sha256-TsemPZkq2Z13/vahRaP7z206BJaCZ1TR6OVv6aeDvyk=",
            "type": "url",
            "url": "https://craigrbroughton.gallery.vsassets.io/_apis/public/gallery/publisher/craigrbroughton/extension/htmx-attributes/0.8.0/assetbyname/Microsoft.VisualStudio.Services.VSIXPackage"
        },
        "version": "0.8.0"
    },
    "mypy-type-checker": {
        "cargoLocks": null,
        "date": null,
        "extract": null,
        "name": "mypy-type-checker",
        "passthru": {
            "name": "mypy-type-checker",
            "publisher": "ms-python"
        },
        "pinned": false,
        "src": {
            "name": "mypy-type-checker-2025.1.10381011.zip",
            "sha256": "sha256-boKUxLOAgQJP13zX/NMhg1MtcrPVQJt5gLbxI7gVSu4=",
            "type": "url",
            "url": "https://ms-python.gallery.vsassets.io/_apis/public/gallery/publisher/ms-python/extension/mypy-type-checker/2025.1.10381011/assetbyname/Microsoft.VisualStudio.Services.VSIXPackage"
        },
        "version": "2025.1.10381011"
    },
    "prom": {
        "cargoLocks": null,
        "date": null,
        "extract": null,
        "name": "prom",
        "passthru": {
            "name": "prom",
            "publisher": "ventura"
        },
        "pinned": false,
        "src": {
            "name": "prom-1.3.3.zip",
            "sha256": "sha256-h8pRrPzmu8+5ZiOLALjackr4zWuFAqi1ex7Gp2iOZKk=",
            "type": "url",
            "url": "https://ventura.gallery.vsassets.io/_apis/public/gallery/publisher/ventura/extension/prom/1.3.3/assetbyname/Microsoft.VisualStudio.Services.VSIXPackage"
        },
        "version": "1.3.3"
    },
    "rasi": {
        "cargoLocks": null,
        "date": null,
        "extract": null,
        "name": "rasi",
        "passthru": {
            "name": "rasi",
            "publisher": "dlasagno"
        },
        "pinned": false,
        "src": {
            "name": "rasi-1.0.0.zip",
            "sha256": "sha256-s60alej3cNAbSJxsRlIRE2Qha6oAsmcOBbWoqp+w6fk=",
            "type": "url",
            "url": "https://dlasagno.gallery.vsassets.io/_apis/public/gallery/publisher/dlasagno/extension/rasi/1.0.0/assetbyname/Microsoft.VisualStudio.Services.VSIXPackage"
        },
        "version": "1.0.0"
    },
    "remote-explorer": {
        "cargoLocks": null,
        "date": null,
        "extract": null,
        "name": "remote-explorer",
        "passthru": {
            "name": "remote-explorer",
            "publisher": "ms-vscode"
        },
        "pinned": false,
        "src": {
            "name": "remote-explorer-0.5.2025010909.zip",
            "sha256": "sha256-wAxei9TYi23O+KkG6cxoCv9dkJi9FolFTUeDoQCzYB4=",
            "type": "url",
            "url": "https://ms-vscode.gallery.vsassets.io/_apis/public/gallery/publisher/ms-vscode/extension/remote-explorer/0.5.2025010909/assetbyname/Microsoft.VisualStudio.Services.VSIXPackage"
        },
        "version": "0.5.2025010909"
    },
    "remotehub": {
        "cargoLocks": null,
        "date": null,
        "extract": null,
        "name": "remotehub",
        "passthru": {
            "name": "remotehub",
            "publisher": "github"
        },
        "pinned": false,
        "src": {
            "name": "remotehub-0.65.2024112101.zip",
            "sha256": "sha256-Xb28yff0tiQDUuwC5Mv0rwXqLgZOU4B3KZAht78NfFU=",
            "type": "url",
            "url": "https://github.gallery.vsassets.io/_apis/public/gallery/publisher/github/extension/remotehub/0.65.2024112101/assetbyname/Microsoft.VisualStudio.Services.VSIXPackage"
        },
        "version": "0.65.2024112101"
    },
    "sqlite-viewer": {
        "cargoLocks": null,
        "date": null,
        "extract": null,
        "name": "sqlite-viewer",
        "passthru": {
            "name": "sqlite-viewer",
            "publisher": "qwtel"
        },
        "pinned": false,
        "src": {
            "name": "sqlite-viewer-0.10.1.zip",
            "sha256": "sha256-dEaD2GH7aNWcF3hvXtZ2wh5/IUE1KZzHBgTxIP35ZwI=",
            "type": "url",
            "url": "https://qwtel.gallery.vsassets.io/_apis/public/gallery/publisher/qwtel/extension/sqlite-viewer/0.10.1/assetbyname/Microsoft.VisualStudio.Services.VSIXPackage"
        },
        "version": "0.10.1"
    },
    "sqltools": {
        "cargoLocks": null,
        "date": null,
        "extract": null,
        "name": "sqltools",
        "passthru": {
            "name": "sqltools",
            "publisher": "mtxr"
        },
        "pinned": false,
        "src": {
            "name": "sqltools-0.28.3.zip",
            "sha256": "sha256-bTrHAhj8uwzRIImziKsOizZf8+k3t+VrkOeZrFx7SH8=",
            "type": "url",
            "url": "https://mtxr.gallery.vsassets.io/_apis/public/gallery/publisher/mtxr/extension/sqltools/0.28.3/assetbyname/Microsoft.VisualStudio.Services.VSIXPackage"
        },
        "version": "0.28.3"
    },
    "sqltools-driver-pg": {
        "cargoLocks": null,
        "date": null,
        "extract": null,
        "name": "sqltools-driver-pg",
        "passthru": {
            "name": "sqltools-driver-pg",
            "publisher": "mtxr"
        },
        "pinned": false,
        "src": {
            "name": "sqltools-driver-pg-0.5.4.zip",
            "sha256": "sha256-XnPTMFNgMGT2tJe8WlmhMB3DluvMZx9Ee2w7xMCzLYM=",
            "type": "url",
            "url": "https://mtxr.gallery.vsassets.io/_apis/public/gallery/publisher/mtxr/extension/sqltools-driver-pg/0.5.4/assetbyname/Microsoft.VisualStudio.Services.VSIXPackage"
        },
        "version": "0.5.4"
    },
    "sqltools-driver-sqlite": {
        "cargoLocks": null,
        "date": null,
        "extract": null,
        "name": "sqltools-driver-sqlite",
        "passthru": {
            "name": "sqltools-driver-sqlite",
            "publisher": "mtxr"
        },
        "pinned": false,
        "src": {
            "name": "sqltools-driver-sqlite-0.5.1.zip",
            "sha256": "sha256-wFgb6wDSgPbPtEVKbHcUeURqbVAqDsEEhFUcBhQtmF8=",
            "type": "url",
            "url": "https://mtxr.gallery.vsassets.io/_apis/public/gallery/publisher/mtxr/extension/sqltools-driver-sqlite/0.5.1/assetbyname/Microsoft.VisualStudio.Services.VSIXPackage"
        },
        "version": "0.5.1"
    },
    "tailwind-color-matcher": {
        "cargoLocks": null,
        "date": null,
        "extract": null,
        "name": "tailwind-color-matcher",
        "passthru": {
            "name": "tailwind-color-matcher",
            "publisher": "OmriGrossman"
        },
        "pinned": false,
        "src": {
            "name": "tailwind-color-matcher-1.0.8.zip",
            "sha256": "sha256-WfFg1h5tY43W9YqgXkHDlxjRquFupuvLBwotTw0XoNk=",
            "type": "url",
            "url": "https://OmriGrossman.gallery.vsassets.io/_apis/public/gallery/publisher/OmriGrossman/extension/tailwind-color-matcher/1.0.8/assetbyname/Microsoft.VisualStudio.Services.VSIXPackage"
        },
        "version": "1.0.8"
    },
    "tailwind-docs": {
        "cargoLocks": null,
        "date": null,
        "extract": null,
        "name": "tailwind-docs",
        "passthru": {
            "name": "tailwind-docs",
            "publisher": "austenc"
        },
        "pinned": false,
        "src": {
            "name": "tailwind-docs-2.1.0.zip",
            "sha256": "sha256-EB3ggxo2NqiH8yVpsNzDRb+fvsd6Qd5aXRM6FoZn5k8=",
            "type": "url",
            "url": "https://austenc.gallery.vsassets.io/_apis/public/gallery/publisher/austenc/extension/tailwind-docs/2.1.0/assetbyname/Microsoft.VisualStudio.Services.VSIXPackage"
        },
        "version": "2.1.0"
    },
    "tailwind-fold": {
        "cargoLocks": null,
        "date": null,
        "extract": null,
        "name": "tailwind-fold",
        "passthru": {
            "name": "tailwind-fold",
            "publisher": "stivo"
        },
        "pinned": false,
        "src": {
            "name": "tailwind-fold-0.2.0.zip",
            "sha256": "sha256-yH3eA5jgBwxqnpFQkg91KQMkQps5iM1v783KQkQcWUU=",
            "type": "url",
            "url": "https://stivo.gallery.vsassets.io/_apis/public/gallery/publisher/stivo/extension/tailwind-fold/0.2.0/assetbyname/Microsoft.VisualStudio.Services.VSIXPackage"
        },
        "version": "0.2.0"
    },
    "templ": {
        "cargoLocks": null,
        "date": null,
        "extract": null,
        "name": "templ",
        "passthru": {
            "name": "templ",
            "publisher": "a-h"
        },
        "pinned": false,
        "src": {
            "name": "templ-0.0.33.zip",
            "sha256": "sha256-Q9ZM3DPxB5bW/ob+aTgQZCl1OaSDvDGluqhqd4k8GIM=",
            "type": "url",
            "url": "https://a-h.gallery.vsassets.io/_apis/public/gallery/publisher/a-h/extension/templ/0.0.33/assetbyname/Microsoft.VisualStudio.Services.VSIXPackage"
        },
        "version": "0.0.33"
    },
    "vscode-gitops-tools": {
        "cargoLocks": null,
        "date": null,
        "extract": null,
        "name": "vscode-gitops-tools",
        "passthru": {
            "name": "vscode-gitops-tools",
            "publisher": "weaveworks"
        },
        "pinned": false,
        "src": {
            "name": "vscode-gitops-tools-0.27.0.zip",
            "sha256": "sha256-7MCKDnHCot/CL/SqZ2WuTxbqFdF75EC5WC+OxW0dcaE=",
            "type": "url",
            "url": "https://weaveworks.gallery.vsassets.io/_apis/public/gallery/publisher/weaveworks/extension/vscode-gitops-tools/0.27.0/assetbyname/Microsoft.VisualStudio.Services.VSIXPackage"
        },
        "version": "0.27.0"
    },
    "vscode-jsonnet": {
        "cargoLocks": null,
        "date": null,
        "extract": null,
        "name": "vscode-jsonnet",
        "passthru": {
            "name": "vscode-jsonnet",
            "publisher": "grafana"
        },
        "pinned": false,
        "src": {
            "name": "vscode-jsonnet-0.7.2.zip",
            "sha256": "sha256-Q8VzXzTdHo9h5+eCHHF1bPomPEbRsvouJcUfmFUDGMU=",
            "type": "url",
            "url": "https://grafana.gallery.vsassets.io/_apis/public/gallery/publisher/grafana/extension/vscode-jsonnet/0.7.2/assetbyname/Microsoft.VisualStudio.Services.VSIXPackage"
        },
        "version": "0.7.2"
    },
    "vscode-postgresql-client2": {
        "cargoLocks": null,
        "date": null,
        "extract": null,
        "name": "vscode-postgresql-client2",
        "passthru": {
            "name": "vscode-postgresql-client2",
            "publisher": "cweijan"
        },
        "pinned": false,
        "src": {
            "name": "vscode-postgresql-client2-8.1.4.zip",
            "sha256": "sha256-hfsYLvE0itiRZD9lzMSNTwcMeYgrwKRY+hX+nFLvIeI=",
            "type": "url",
            "url": "https://cweijan.gallery.vsassets.io/_apis/public/gallery/publisher/cweijan/extension/vscode-postgresql-client2/8.1.4/assetbyname/Microsoft.VisualStudio.Services.VSIXPackage"
        },
        "version": "8.1.4"
    },
    "vscode-speech": {
        "cargoLocks": null,
        "date": null,
        "extract": null,
        "name": "vscode-speech",
        "passthru": {
            "name": "vscode-speech",
            "publisher": "ms-vscode"
        },
        "pinned": false,
        "src": {
            "name": "vscode-speech-0.12.1.zip",
            "sha256": "sha256-fxmaPI7uq7DQlzgJc8RcZzHDOwMuodSCf9TkLU9+/+k=",
            "type": "url",
            "url": "https://ms-vscode.gallery.vsassets.io/_apis/public/gallery/publisher/ms-vscode/extension/vscode-speech/0.12.1/assetbyname/Microsoft.VisualStudio.Services.VSIXPackage"
        },
        "version": "0.12.1"
    },
    "vscode-thunder-client": {
        "cargoLocks": null,
        "date": null,
        "extract": null,
        "name": "vscode-thunder-client",
        "passthru": {
            "name": "vscode-thunder-client",
            "publisher": "rangav"
        },
        "pinned": false,
        "src": {
            "name": "vscode-thunder-client-2.34.1.zip",
            "sha256": "sha256-dz7wf6GecpRBQCuZXfwRDGIEbVYCaptWi7nxKUveFTI=",
            "type": "url",
            "url": "https://rangav.gallery.vsassets.io/_apis/public/gallery/publisher/rangav/extension/vscode-thunder-client/2.34.1/assetbyname/Microsoft.VisualStudio.Services.VSIXPackage"
        },
        "version": "2.34.1"
    },
    "yuck": {
        "cargoLocks": null,
        "date": null,
        "extract": null,
        "name": "yuck",
        "passthru": {
            "name": "yuck",
            "publisher": "eww-yuck"
        },
        "pinned": false,
        "src": {
            "name": "yuck-0.0.3.zip",
            "sha256": "sha256-DITgLedaO0Ifrttu+ZXkiaVA7Ua5RXc4jXQHPYLqrcM=",
            "type": "url",
            "url": "https://eww-yuck.gallery.vsassets.io/_apis/public/gallery/publisher/eww-yuck/extension/yuck/0.0.3/assetbyname/Microsoft.VisualStudio.Services.VSIXPackage"
        },
        "version": "0.0.3"
    }
}